<?xml version="1.0" encoding="utf-8"?><Episode>
  <id>5939659</id>
  <Combined_episodenumber>5.0</Combined_episodenumber>
  <Combined_season>4</Combined_season>
  <DVD_chapter></DVD_chapter>
  <DVD_discid></DVD_discid>
  <DVD_episodenumber>5.0</DVD_episodenumber>
  <DVD_season>4</DVD_season>
  <Director>John F. Showalter</Director>
  <EpImgFlag>2</EpImgFlag>
  <EpisodeName>The Tinder Box</EpisodeName>
  <EpisodeNumber>5</EpisodeNumber>
  <FirstAired>2017-03-01</FirstAired>
  <GuestStars></GuestStars>
  <IMDB_ID>tt6035900</IMDB_ID>
  <Language>pl</Language>
  <Overview>Clarke makes a desperate plea with a former allied force in an attempt to avoid a war and ensure the survival of her people.</Overview>
  <ProductionCode></ProductionCode>
  <Rating>7.8</Rating>
  <RatingCount>4</RatingCount>
  <SeasonNumber>4</SeasonNumber>
  <Writer>Morgan Gendel</Writer>
  <absolute_number>50</absolute_number>
  <filename>episodes/268592/5939659.jpg</filename>
  <is_movie>0</is_movie>
  <lastupdated>1493250124</lastupdated>
  <seasonid>680431</seasonid>
  <seriesid>268592</seriesid>
  <thumb_added>2017-02-24 16:26:15</thumb_added>
  <thumb_height>225</thumb_height>
  <thumb_width>400</thumb_width>
</Episode>