<?xml version="1.0" encoding="utf-8"?><Episode>
  <id>4370117</id>
  <Combined_episodenumber>21</Combined_episodenumber>
  <Combined_season>1</Combined_season>
  <DVD_chapter></DVD_chapter>
  <DVD_discid></DVD_discid>
  <DVD_episodenumber></DVD_episodenumber>
  <DVD_season></DVD_season>
  <Director></Director>
  <EpImgFlag>2</EpImgFlag>
  <EpisodeName>The Haunting of Griffin Rock</EpisodeName>
  <EpisodeNumber>21</EpisodeNumber>
  <FirstAired>2012-07-28</FirstAired>
  <GuestStars></GuestStars>
  <IMDB_ID></IMDB_ID>
  <Language>pl</Language>
  <Overview>Ghosts haunt and terrorize the residents of Griffin Rock.</Overview>
  <ProductionCode>121</ProductionCode>
  <Rating></Rating>
  <RatingCount>0</RatingCount>
  <SeasonNumber>1</SeasonNumber>
  <Writer></Writer>
  <absolute_number></absolute_number>
  <filename>episodes/256349/4370117.jpg</filename>
  <is_movie>0</is_movie>
  <lastupdated>1488605656</lastupdated>
  <seasonid>485760</seasonid>
  <seriesid>256349</seriesid>
  <thumb_added>2015-06-20 15:29:22</thumb_added>
  <thumb_height>225</thumb_height>
  <thumb_width>400</thumb_width>
</Episode>