<?xml version="1.0" encoding="utf-8"?><Episode>
  <id>5069153</id>
  <Combined_episodenumber>7</Combined_episodenumber>
  <Combined_season>3</Combined_season>
  <DVD_chapter></DVD_chapter>
  <DVD_discid></DVD_discid>
  <DVD_episodenumber></DVD_episodenumber>
  <DVD_season></DVD_season>
  <Director></Director>
  <EpImgFlag></EpImgFlag>
  <EpisodeName>Bugs in the System</EpisodeName>
  <EpisodeNumber>7</EpisodeNumber>
  <FirstAired>2014-12-06</FirstAired>
  <GuestStars></GuestStars>
  <IMDB_ID></IMDB_ID>
  <Language>pl</Language>
  <Overview>Doctor Morocco escapes and proves that even the smallest of pests can become an enormous threat to all of Griffin Rock.</Overview>
  <ProductionCode>157</ProductionCode>
  <Rating></Rating>
  <RatingCount>0</RatingCount>
  <SeasonNumber>3</SeasonNumber>
  <Writer></Writer>
  <absolute_number></absolute_number>
  <filename></filename>
  <is_movie>0</is_movie>
  <lastupdated>1426611945</lastupdated>
  <seasonid>601749</seasonid>
  <seriesid>256349</seriesid>
  <thumb_added></thumb_added>
  <thumb_height></thumb_height>
  <thumb_width></thumb_width>
</Episode>