<?xml version="1.0" encoding="utf-8"?><Episode>
  <id>5148407</id>
  <Combined_episodenumber>4.0</Combined_episodenumber>
  <Combined_season>2</Combined_season>
  <DVD_chapter></DVD_chapter>
  <DVD_discid></DVD_discid>
  <DVD_episodenumber>4.0</DVD_episodenumber>
  <DVD_season>2</DVD_season>
  <Director>Alec Berg</Director>
  <EpImgFlag>2</EpImgFlag>
  <EpisodeName>The Lady</EpisodeName>
  <EpisodeNumber>4</EpisodeNumber>
  <FirstAired>2015-05-03</FirstAired>
  <GuestStars></GuestStars>
  <IMDB_ID>tt3682586</IMDB_ID>
  <Language>pl</Language>
  <Overview>Richard butts heads with Erlich over a prospective hire, while Dinesh and Gilfoyle become suspicious that a new employee they recommended is commanding a higher salary. Big Head gets a surprising promotion at Hooli. At a board meeting, Monica and Richard find themselves outvoted; Jared institutes a workplace harassment policy.</Overview>
  <ProductionCode></ProductionCode>
  <Rating>7.8</Rating>
  <RatingCount>20</RatingCount>
  <SeasonNumber>2</SeasonNumber>
  <Writer>Carson Mell</Writer>
  <absolute_number>12</absolute_number>
  <filename>episodes/277165/5148407.jpg</filename>
  <is_movie>0</is_movie>
  <lastupdated>1497101713</lastupdated>
  <seasonid>608408</seasonid>
  <seriesid>277165</seriesid>
  <thumb_added>2015-05-03 06:42:28</thumb_added>
  <thumb_height>225</thumb_height>
  <thumb_width>400</thumb_width>
</Episode>