<?xml version="1.0" encoding="utf-8"?><Episode>
  <id>5493958</id>
  <Combined_episodenumber>6.0</Combined_episodenumber>
  <Combined_season>3</Combined_season>
  <DVD_chapter></DVD_chapter>
  <DVD_discid></DVD_discid>
  <DVD_episodenumber>6.0</DVD_episodenumber>
  <DVD_season>3</DVD_season>
  <Director>Eric Appel</Director>
  <EpImgFlag>2</EpImgFlag>
  <EpisodeName>Bachmanity Insanity</EpisodeName>
  <EpisodeNumber>6</EpisodeNumber>
  <FirstAired>2016-05-29</FirstAired>
  <GuestStars></GuestStars>
  <IMDB_ID>tt5218484</IMDB_ID>
  <Language>pl</Language>
  <Overview>Richard’s new relationship is threatened by neuroses. Big Head and Erlich’s launch party has snags. Dinesh falls for a foreign coworker. </Overview>
  <ProductionCode></ProductionCode>
  <Rating>7.9</Rating>
  <RatingCount>11</RatingCount>
  <SeasonNumber>3</SeasonNumber>
  <Writer>Carson Mell</Writer>
  <absolute_number>24</absolute_number>
  <filename>episodes/277165/5493958.jpg</filename>
  <is_movie>0</is_movie>
  <lastupdated>1495620175</lastupdated>
  <seasonid>648622</seasonid>
  <seriesid>277165</seriesid>
  <thumb_added>2016-05-26 07:24:57</thumb_added>
  <thumb_height>225</thumb_height>
  <thumb_width>400</thumb_width>
</Episode>